django_graphql_persist-0.1.1.dist-info/DESCRIPTION.rst
django_graphql_persist-0.1.1.dist-info/METADATA
django_graphql_persist-0.1.1.dist-info/RECORD
django_graphql_persist-0.1.1.dist-info/WHEEL
django_graphql_persist-0.1.1.dist-info/metadata.json
django_graphql_persist-0.1.1.dist-info/top_level.txt
graphql_persist/__init__.py
graphql_persist/cache.py
graphql_persist/exceptions.py
graphql_persist/middleware.py
graphql_persist/parser.py
graphql_persist/query.py
graphql_persist/settings.py
graphql_persist/versioning.py
graphql_persist/loaders/__init__.py
graphql_persist/loaders/app_directories.py
graphql_persist/loaders/base.py
graphql_persist/loaders/cached.py
graphql_persist/loaders/engine.py
graphql_persist/loaders/exceptions.py
graphql_persist/loaders/filesystem.py
graphql_persist/loaders/parser.py
graphql_persist/loaders/url.py
graphql_persist/renderers/__init__.py
graphql_persist/renderers/base.py
graphql_persist/renderers/relay.py
